mlr/Data_plots.py
mlr/Diagnostics_plots.py
mlr/Inference.py
mlr/MLR.py
mlr/Metrics.py
mlr/Multicollinearity.py
mlr/Outliers.py
mlr/__init__.py
mlr-0.1.0.dist-info/LICENSE
mlr-0.1.0.dist-info/METADATA
mlr-0.1.0.dist-info/WHEEL
mlr-0.1.0.dist-info/top_level.txt
mlr-0.1.0.dist-info/RECORD
